chartparse/__init__.py
chartparse/chart.py
chartparse/event.py
chartparse/exceptions.py
chartparse/globalevents.py
chartparse/hints.py
chartparse/instrument.py
chartparse/metadata.py
chartparse/sync.py
chartparse/tick.py
chartparse/time.py
chartparse/track.py
chartparse/util.py
tests/helpers/__init__.py
tests/helpers/defaults.py
tests/helpers/event.py
tests/helpers/fruit.py
tests/helpers/globalevents.py
tests/helpers/instrument.py
tests/helpers/lines.py
tests/helpers/log.py
tests/helpers/sync.py
tests/helpers/testcase.py
tests/helpers/tick.py
tests/helpers/unsafe.py
chartparse-0.3.1.dist-info/LICENSE
chartparse-0.3.1.dist-info/METADATA
chartparse-0.3.1.dist-info/WHEEL
chartparse-0.3.1.dist-info/entry_points.txt
chartparse-0.3.1.dist-info/top_level.txt
chartparse-0.3.1.dist-info/RECORD
