Metadata-Version: 2.1
Name: chartparse
Version: 0.3.1
Summary: A library for parsing Guitar Hero .chart files.
Home-page: https://github.com/AWConant/chartparse/
Author: AWConant
License-File: LICENSE
Requires-Dist: sphinx (==4.5.0)
Requires-Dist: sphinx-rtd-theme (==1.0.0)
Requires-Dist: sphinx-toolbox (==3.1.1)
Provides-Extra: test
Requires-Dist: black (==22.3.0) ; extra == 'test'
Requires-Dist: codecov (==2.1.12) ; extra == 'test'
Requires-Dist: coverage (==6.4.1) ; extra == 'test'
Requires-Dist: flake8 (==4.0.1) ; extra == 'test'
Requires-Dist: flake8-rst-docstrings (==0.3.0) ; extra == 'test'
Requires-Dist: gitchangelog (==3.0.4) ; extra == 'test'
Requires-Dist: isort (==5.10.1) ; extra == 'test'
Requires-Dist: mypy (==0.961) ; extra == 'test'
Requires-Dist: pytest (==7.1.2) ; extra == 'test'
Requires-Dist: pytest-cov (==3.0.0) ; extra == 'test'
Requires-Dist: pytest-mock (==3.8.1) ; extra == 'test'
